rushd/__init__.py
rushd/flow.py
rushd/io.py
rushd/plot.py
rushd/well_mapper.py
rushd-0.5.1.dist-info/licenses/LICENSE
rushd-0.5.1.dist-info/METADATA
rushd-0.5.1.dist-info/WHEEL
rushd-0.5.1.dist-info/top_level.txt
rushd-0.5.1.dist-info/RECORD
